pyvin/__init__.py
pyvin/errors.py
pyvin/pyvin.py
pyvin/utils.py
tests/__init__.py
tests/test_pyvin.py
tests/test_vincheck.py
tests/vin_samples.py
pyvin-0.0.2.dist-info/LICENSE
pyvin-0.0.2.dist-info/METADATA
pyvin-0.0.2.dist-info/WHEEL
pyvin-0.0.2.dist-info/top_level.txt
pyvin-0.0.2.dist-info/RECORD
