Metadata-Version: 2.1
Name: pyvin
Version: 0.0.2
Summary: Python VIN decoder
Home-page: https://github.com/arpuffer/pyvin
Author: Alex Puffer
License: UNKNOWN
Platform: UNKNOWN
Classifier: Programming Language :: Python :: 3
Classifier: License :: OSI Approved :: MIT License
Classifier: Operating System :: OS Independent
Provides: pyvin
Requires-Python: >=3.6
